lura/__init__.py
lura/assets.py
lura/at.py
lura/attrs.py
lura/click.py
lura/fs.py
lura/hash.py
lura/iters.py
lura/logutils.py
lura/messaging.py
lura/net.py
lura/random.py
lura/rpc.py
lura/run.py
lura/strings.py
lura/threads.py
lura/time.py
lura/utils.py
lura/expanders/__init__.py
lura/expanders/jinja2.py
lura/formats/__init__.py
lura/formats/csv.py
lura/formats/json.py
lura/formats/pyaml.py
lura/formats/yaml.py
lura-1.1.0.dist-info/LICENSE
lura-1.1.0.dist-info/METADATA
lura-1.1.0.dist-info/WHEEL
lura-1.1.0.dist-info/entry_points.txt
lura-1.1.0.dist-info/top_level.txt
lura-1.1.0.dist-info/zip-safe
lura-1.1.0.dist-info/RECORD
