Metadata-Version: 2.1
Name: lura
Version: 1.1.0
Summary: a bag of tricks
Home-page: https://github.com/ecks0/lura
Author: Nick Zigarovich
Author-email: nick@zigarovich.io
License: UNKNOWN
Platform: UNKNOWN
Requires-Python: >= 3.6
Requires-Dist: PyYAML (>=3.13)
Requires-Dist: cryptography (>=2.7)
Requires-Dist: deepmerge (>=0.1.0)
Requires-Dist: pyaml (>=20.4.0)
Requires-Dist: requests (>=2.21.0)
Requires-Dist: rpyc (>=4.1.1)
Requires-Dist: schedule (>=0.6.0)
